flask_babel/__init__.py
flask_babel/cli.py
flask_babel/speaklater.py
flask_babel_hyper-5.1.0.dist-info/LICENSE
flask_babel_hyper-5.1.0.dist-info/METADATA
flask_babel_hyper-5.1.0.dist-info/WHEEL
flask_babel_hyper-5.1.0.dist-info/RECORD
